tensorgp/__init__.py
tensorgp/engine.py
tensorgp-0.0.4.dist-info/LICENSE
tensorgp-0.0.4.dist-info/METADATA
tensorgp-0.0.4.dist-info/WHEEL
tensorgp-0.0.4.dist-info/top_level.txt
tensorgp-0.0.4.dist-info/RECORD
